Metadata-Version: 2.4
Name: bento-sc
Version: 0.0.8
Summary: BENchmarking Transformer-Obtained Single-Cell embeddings
Home-page: https://github.com/gdewael/bento-sc
Author: Gaetan De Waele
Author-email: gaetandewaele@hotmail.com
Requires-Python: >=3.11
License-File: LICENSE
Requires-Dist: numpy
Requires-Dist: torch
Requires-Dist: lightning
Requires-Dist: h5torch>=0.2.13
Requires-Dist: bio-attention
Requires-Dist: scipy
Requires-Dist: einops
Requires-Dist: pyyaml
Requires-Dist: scanpy
Requires-Dist: anndata
Requires-Dist: cellxgene-census
Requires-Dist: tqdm
Requires-Dist: obonet
Requires-Dist: networkx
Requires-Dist: tensorboard
Requires-Dist: bbknn
Requires-Dist: scib
Requires-Dist: scikit-learn
Dynamic: license-file
